clax/__init__.py
clax/loss.py
clax/metrics.py
clax/trainer.py
clax/config/dataset/baidu-ultr-uva.yaml
clax/config/dataset/baidu-ultr.yaml
clax/config/dataset/yandex.yaml
clax/config/model/ccm.yaml
clax/config/model/cm.yaml
clax/config/model/dbn.yaml
clax/config/model/dcm.yaml
clax/config/model/dctr.yaml
clax/config/model/drctr.yaml
clax/config/model/gctr.yaml
clax/config/model/pbm.yaml
clax/config/model/rctr.yaml
clax/config/model/sdbn.yaml
clax/config/model/ubm.yaml
clax/config/parameter/attraction/deep-cross.yaml
clax/config/parameter/attraction/deep.yaml
clax/config/parameter/attraction/linear.yaml
clax/config/parameter/attraction/embedding/full.yaml
clax/config/parameter/attraction/embedding/hash.yaml
clax/config/parameter/attraction/embedding/qr.yaml
clax/config/parameter/attraction/embedding/robe-d.yaml
clax/config/parameter/continuation/position.yaml
clax/config/parameter/examination/position.yaml
clax/config/parameter/satisfaction/deep-cross.yaml
clax/config/parameter/satisfaction/deep.yaml
clax/config/parameter/satisfaction/global.yaml
clax/config/parameter/satisfaction/linear.yaml
clax/config/parameter/satisfaction/embedding/full.yaml
clax/config/parameter/satisfaction/embedding/hash.yaml
clax/config/parameter/satisfaction/embedding/qr.yaml
clax/config/parameter/satisfaction/embedding/robe-d.yaml
clax/datasets/__init__.py
clax/datasets/baidu.py
clax/datasets/parquet.py
clax/datasets/utils.py
clax/datasets/yandex.py
clax/models/__init__.py
clax/models/base.py
clax/models/ccm.py
clax/models/cm.py
clax/models/ctr.py
clax/models/dbn.py
clax/models/dcm.py
clax/models/mixture.py
clax/models/pbm.py
clax/models/ubm.py
clax/parameters/__init__.py
clax/parameters/base.py
clax/parameters/deep.py
clax/parameters/deep_cross.py
clax/parameters/defaults.py
clax/parameters/globals.py
clax/parameters/linear.py
clax/parameters/embeddings/__init__.py
clax/parameters/embeddings/base.py
clax/parameters/embeddings/compositional.py
clax/parameters/embeddings/hashing.py
clax_models-0.1.0.dist-info/licenses/LICENSE
clax_models-0.1.0.dist-info/METADATA
clax_models-0.1.0.dist-info/WHEEL
clax_models-0.1.0.dist-info/top_level.txt
clax_models-0.1.0.dist-info/RECORD
