Metadata-Version: 2.4
Name: clax-models
Version: 0.1.0
Summary: A fast and flexible library for gradient-based click models
Requires-Python: >=3.10
License-File: LICENSE
Requires-Dist: jax>=0.6.0
Requires-Dist: flax<0.12.0,>=0.10.6
Requires-Dist: hydra-core>=1.3.2
Requires-Dist: optax>=0.2.4
Requires-Dist: pandas>=2.3.2
Requires-Dist: pyarrow>=21.0.0
Requires-Dist: progress-table>=3.1.2
Requires-Dist: rax>=0.4.0
Requires-Dist: torch>=2.7.0
Provides-Extra: cuda12
Requires-Dist: jax[cuda12]>=0.6.0; extra == "cuda12"
Dynamic: license-file
